src/ALU.sv
module ALU (
    input logic signed [31:0] A,
    input logic signed [31:0] B,

    input logic [3:0] ALUOp,

    output logic signed [31:0] ALURes = 0
);

    always @* begin
        case (ALUOp)
            4'b0000: ALURes = A + B;
            4'b1000: ALURes = A - B;
            4'b0001: ALURes = A << B;
            4'b0010: ALURes = A < B;
            4'b0011: ALURes = $unsigned(A) < $unsigned(B);
            4'b0100: ALURes = A ^ B;
            4'b0101: ALURes = A >> B;
            4'b1101: ALURes = A >>> B;
            4'b0110: ALURes = A | B;
            4'b0111: ALURes = A & B;
            4'b1001: ALURes = B; 
        endcase
    end
    
endmodule

tb/alu_tb.sv
module alu_tb;
    logic signed [31:0] A, B;
    logic [3:0] ALUOp;
    logic signed [31:0] ALURes;

    ALU dut (
        .A(A),
        .B(B),
        .ALUOp(ALUOp),
        .ALURes(ALURes)
    );

    initial begin
        $dumpfile("sim/alu_tb.vcd");
        $dumpvars(0, alu_tb);

        // Test ADD
        A = 10; B = 5; ALUOp = 4'b0000; #10;
        if (ALURes !== 15) $error("ADD failed: 10 + 5 = %d", ALURes);

        // Test SUB
        A = 10; B = 5; ALUOp = 4'b1000; #10;
        if (ALURes !== 5) $error("SUB failed: 10 - 5 = %d", ALURes);

        // Test AND
        A = 32'hF0F0F0F0; B = 32'h0F0F0F0F; ALUOp = 4'b0111; #10;
        if (ALURes !== 32'h00000000) $error("AND failed");

        // Test OR
        A = 32'hF0F0F0F0; B = 32'h0F0F0F0F; ALUOp = 4'b0110; #10;
        if (ALURes !== 32'hFFFFFFFF) $error("OR failed");

        // Test SLT
        A = 10; B = 20; ALUOp = 4'b0010; #10;
        if (ALURes !== 1) $error("SLT failed: 10 < 20");
        
        A = 20; B = 10; ALUOp = 4'b0010; #10;
        if (ALURes !== 0) $error("SLT failed: 20 < 10");

        // Test XOR
        A = 32'hF0F0F0F0; B = 32'hFFFF0000; ALUOp = 4'b0100; #10;
        if (ALURes !== 32'h0F0FF0F0) $error("XOR failed");

        // Test SLL (Shift Left Logical)
        A = 32'h00000001; B = 4; ALUOp = 4'b0001; #10;
        if (ALURes !== 32'h00000010) $error("SLL failed: 1 << 4");

        // Test SRL (Shift Right Logical)
        A = 32'hF0000000; B = 4; ALUOp = 4'b0101; #10;
        if (ALURes !== 32'h0F000000) $error("SRL failed: F0000000 >> 4");

        // Test SRA (Shift Right Arithmetic)
        A = 32'hF0000000; B = 4; ALUOp = 4'b1101; #10;
        if (ALURes !== 32'hFF000000) $error("SRA failed: F0000000 >>> 4");

        $display("ALU Testbench Completed");
        $finish;
    end
endmodule

sim/alu_tb.vcd
$date
	Wed Nov 26 20:40:36 2025
$end
$version
	Icarus Verilog
$end
$timescale
	1s
$end
$scope module alu_tb $end
$var wire 32 ! ALURes [31:0] $end
$var reg 32 " A [31:0] $end
$var reg 4 # ALUOp [3:0] $end
$var reg 32 $ B [31:0] $end
$scope module dut $end
$var wire 32 % A [31:0] $end
$var wire 4 & ALUOp [3:0] $end
$var wire 32 ' B [31:0] $end
$var reg 32 ( ALURes [31:0] $end
$upscope $end
$upscope $end
$enddefinitions $end
$comment Show the parameter values. $end
$dumpall
$end
#0
$dumpvars
b1111 (
b101 '
b0 &
b1010 %
b101 $
b0 #
b1010 "
b1111 !
$end
#10
b101 !
b101 (
b1000 #
b1000 &
#20
b0 !
b0 (
b111 #
b111 &
b1111000011110000111100001111 $
b1111000011110000111100001111 '
b11110000111100001111000011110000 "
b11110000111100001111000011110000 %
#30
b11111111111111111111111111111111 !
b11111111111111111111111111111111 (
b110 #
b110 &
#40
b1 !
b1 (
b10 #
b10 &
b10100 $
b10100 '
b1010 "
b1010 %
#50
b0 !
b0 (
b1010 $
b1010 '
b10100 "
b10100 %
#60
b1111000011111111000011110000 !
b1111000011111111000011110000 (
b100 #
b100 &
b11111111111111110000000000000000 $
b11111111111111110000000000000000 '
b11110000111100001111000011110000 "
b11110000111100001111000011110000 %
#70
b10000 !
b10000 (
b1 #
b1 &
b100 $
b100 '
b1 "
b1 %
#80
b1111000000000000000000000000 !
b1111000000000000000000000000 (
b101 #
b101 &
b11110000000000000000000000000000 "
b11110000000000000000000000000000 %
#90
b11111111000000000000000000000000 !
b11111111000000000000000000000000 (
b1101 #
b1101 &
